[
  {
    "sentence": "2024年5月17日 下午 12:08|1小时 7分钟 45秒\n\n关键词:\n黄金、美元、投资、全球、信用、货币、中国、资产、重估、基金经理、货币体系、二级市场、风险偏好、资产负债表、国际金融、投资方式、美国国债、投资组合\n\n文字记录:\n对，说的就是你努力的样子，真的很帅，只要你够坚定，每一条都是对的路",
    "entities": []
  },
  {
    "sentence": "财新大学国际金融，除非你不想赢，否则没人能让你输，赢过平凡，赢得梦想，赢过恐惧，赢得掌声，赢过阻碍，赢得尊重，赢到满足，赢到不满足，总有人在为失败找借糕，但你知道，那些打不倒你的，都会让你变得更强",
    "entities": []
  },
  {
    "sentence": "去赢吧，就算跌倒也没关系，就算渺小也没关系，就算孤独也没关系",
    "entities": []
  },
  {
    "sentence": "where you go whoa",
    "entities": []
  },
  {
    "sentence": "就是这样，继续去赢，你很强，你比昨天更强，你比自己更强",
    "entities": []
  },
  {
    "sentence": "新的比赛，新的对手，这是属于你的主场，你的舞台",
    "entities": []
  },
  {
    "sentence": "下一场比赛，下一个对手，见招拆招，再来",
    "entities": []
  },
  {
    "sentence": "自强者用赢，你知道你很厉害吗",
    "entities": []
  },
  {
    "sentence": "下一位准备对手的挑衅",
    "entities": []
  },
  {
    "sentence": "自然的现实，简单来说是最难救的",
    "entities": []
  },
  {
    "sentence": "现实的强大都不足以让你动摇一分一毫",
    "entities": []
  },
  {
    "sentence": "你说我吗",
    "entities": []
  },
  {
    "sentence": "对，说的就是你",
    "entities": []
  },
  {
    "sentence": "你努力的样子真的很帅，只要你够坚定，每一条都是对的路",
    "entities": []
  },
  {
    "sentence": "财经大学国际金融，除非你不想赢，否则没人能让你输",
    "entities": []
  },
  {
    "sentence": "赢过平凡，赢得梦想，赢过恐惧，赢得掌声，赢过阻碍，赢得尊重，赢到满足，赢到不满足",
    "entities": []
  },
  {
    "sentence": "总有人在为失败找借口，但你知道，那些打不倒你的，都会让你变得更强",
    "entities": []
  },
  {
    "sentence": "去赢吧，就算跌倒也没关系，就算渺小也没关系，就算孤独也没关系",
    "entities": []
  },
  {
    "sentence": "here you go whoa",
    "entities": []
  },
  {
    "sentence": "就是这样，继续去赢，你很强，你比昨天更强，你比自己更强",
    "entities": []
  },
  {
    "sentence": "新的比赛，新的对手，这是属于你的主场，你的舞台，下一场比赛，下一个对手，见招拆招再来see，自强者用赢，你知道你很厉害吗",
    "entities": []
  },
  {
    "sentence": "下一位准备对手的挑衅，自然的现实，简单来说是最难救的",
    "entities": []
  },
  {
    "sentence": "现实的强大都不足以让你动摇一分一毫",
    "entities": []
  },
  {
    "sentence": "你说我吗",
    "entities": []
  },
  {
    "sentence": "对，说的就是你",
    "entities": []
  },
  {
    "sentence": "你努力的样子真的很帅，只要你够坚定，每一条都是对的路",
    "entities": []
  },
  {
    "sentence": "财经大学、国际金融，除非你不想赢，否则没人能让你输，赢过平凡，赢得梦想，赢过恐惧，赢得掌声，赢过阻碍，赢得尊重，赢到满足，赢到不满足",
    "entities": []
  },
  {
    "sentence": "总有人在为失败找借高，但你知道那些打不倒你的都会让你变得更强",
    "entities": []
  },
  {
    "sentence": "去赢，就算跌倒也没关系，就算渺小也没关系，就算孤独也没关系",
    "entities": []
  },
  {
    "sentence": "目前的各位观众朋友们，大家下午1点好，大家下午这一时间可能是刚要上班，或者是刚刚结束一个午休，那我们今天就开始今天的这场直播，欢迎来到语音今天直播间，我是本场直播的主持人桃子",
    "entities": []
  },
  {
    "sentence": "今天我们请到了永银基金指数与量化投资部总经理以及永银黄金股 ETF 的基金经理张云总来到我们的直播现场",
    "entities": []
  },
  {
    "sentence": "大家好，这个其实也是我们的一个，大家可能很多朋友已经非常熟悉了，其实我们上周这个两位主播在直播的时候，我们就看到评论里面特别多的人在呼吁我们说把我们的张总请来给我们讲一讲黄金这个事情",
    "entities": []
  },
  {
    "sentence": "然后我们也是就是马不停蹄的去约了我们张总的时间，在我们这个周二的下午，我们想跟张总一起聊一聊黄金最近的一个市场情况，以及最近他对这个金价以及我们黄金股的一些观点",
    "entities": []
  },
  {
    "sentence": "好的，那我们还是可以请这个嘉宾再跟大家来打一个招呼",
    "entities": []
  },
  {
    "sentence": "啊，大家好",
    "entities": []
  },
  {
    "sentence": "好的，那我们就是开始我们今天的直播，我们今天也废话不多说了，我们其实就几个问题，我们把这些问题都聊透",
    "entities": []
  },
  {
    "sentence": "比如说最近金价为什么在涨",
    "entities": []
  },
  {
    "sentence": "那现在这个时点是不是适合上车",
    "entities": []
  },
  {
    "sentence": "以及我们这个投资黄金股的这些标的上，他们都有什么样的区别",
    "entities": []
  },
  {
    "sentence": "以及我们最后就是说我们黄金股跟黄金之间是有一个什么样的关系以及区别",
    "entities": []
  },
  {
    "sentence": "那我们把这些问题都聊透，然后看看我们还有一些朋友有什么样的一个互动，然后咱们去进行一个答疑的环节",
    "entities": []
  },
  {
    "sentence": "好的，那我们就开始第一个问题，其实也很简单，因为大家最近确实这个金价上涨的事情已经是一个每个人都在聊的这样的一个事情了",
    "entities": []
  },
  {
    "sentence": "那也想请张总先给大家来回顾一下最近，嗯，助燃我们这个金价的行情的这些因素到底有哪些",
    "entities": []
  },
  {
    "sentence": "以及其中您觉得比较重要的几点是什么",
    "entities": []
  },
  {
    "sentence": "嗯，跟很多小伙伴聊过很多次，因为我一直特别看好黄金",
    "entities": []
  },
  {
    "sentence": "其实去年的时候，我",
    "entities": []
  },
  {
    "sentence": "在去年这个时候，我就特别在那个时候，大概是在一两 1, 900 点左右啊",
    "entities": []
  },
  {
    "sentence": "那么再往前我在关于瑞信那个时候，大哥，那个时候 1, 600， 1, 700 的时候，我就无数次说那个黄金是有非常大的这样一个机会的",
    "entities": [
      {
        "industry": "黄金",
        "level1": "行业自身情况",
        "level2": "",
        "time_attr": "过去",
        "score": "2",
        "status": "看好上涨",
        "doubt_remark": ""
      }
    ]
  },
  {
    "sentence": "嗯，那么现在大概在 2, 300，我还是说黄金有很大的这样机会，因为每一次黄金的涨幅它要不涨，它这个平台上升，平台跃升的这种涨幅，这种关系啊",
    "entities": [
      {
        "industry": "黄金",
        "level1": "行业自身情况",
        "level2": "价格",
        "time_attr": "过去",
        "score": "2",
        "status": "大幅上涨",
        "doubt_remark": ""
      }
    ]
  },
  {
    "sentence": "那么从布雷顿森林体系破坏以来， 70 年代到现在其实就是搭了几个大的平台和几个大的跃升期，所以黄金是特别适合做右侧的啊",
    "entities": [
      {
        "industry": "黄金",
        "level1": "行业自身情况",
        "level2": "价格",
        "time_attr": "",
        "score": "1",
        "status": "适合右侧",
        "doubt_remark": ""
      }
    ]
  },
  {
    "sentence": "所有的有色金属当中，黄金最适合做右侧，为什么呢",
    "entities": [
      {
        "industry": "黄金",
        "level1": "行业自身情况",
        "level2": "",
        "time_attr": "过去",
        "score": "1",
        "status": "",
        "doubt_remark": ""
      }
    ]
  },
  {
    "sentence": "其他的金属它可能你都可以做个左侧，因为它都存在这样一个，比如说一个斜率向上的这样一个关系啊",
    "entities": [
      {
        "industry": "黄金",
        "level1": "行业自身情况",
        "level2": "",
        "time_attr": "",
        "score": "",
        "status": "",
        "doubt_remark": ""
      }
    ]
  },
  {
    "sentence": "但是黄金大部分时间他躺着是不动的，有可能十年不动，也有可能 15 年不动啊",
    "entities": [
      {
        "industry": "黄金",
        "level1": "行业自身情况",
        "level2": "价格",
        "time_attr": "现在",
        "score": "0",
        "status": "不变",
        "doubt_remark": ""
      }
    ]
  },
  {
    "sentence": "大家去看一下八九十年的黄金， 15 年不动，但是移动起来它的涨幅是非常大的，所以当黄金启动之后，大家其实上车那么其实是一个非常好的这样一个选择，因为黄金比较适合做右侧，那么这一次黄金的右侧机会或者黄金的行情为什么会起来",
    "entities": [
      {
        "industry": "黄金",
        "level1": "行业自身情况",
        "level2": "价格",
        "time_attr": "过去",
        "score": "1",
        "status": "大幅上涨",
        "doubt_remark": ""
      }
    ]
  },
  {
    "sentence": "为什么我前期这么看好黄金",
    "entities": []
  },
  {
    "sentence": "其实最根本的原因就是美元银的太多了，黄金的兑价物是美元，这一点大家都知道，每个人都知道黄金兑价物是美元，或者说美元，黄金是所有全球所有的法币的对手，因为所有的法币对应的都是政府的信用，那么黄金对应的是什么",
    "entities": [
      {
        "industry": "黄金",
        "level1": "国家政策方向",
        "level2": "对价物",
        "time_attr": "始终",
        "score": "1",
        "status": "是政府的信用",
        "doubt_remark": ""
      }
    ]
  },
  {
    "sentence": "黄金对应的实实在在的资产，哈哈哈哈，它是真金白银，所谓的真金白银那么好啊",
    "entities": [
      {
        "industry": "黄金",
        "level1": "行业自身情况",
        "level2": "价格",
        "time_attr": "现在",
        "score": "1",
        "status": "",
        "doubt_remark": ""
      }
    ]
  },
  {
    "sentence": "我们所有的货币，它的毛是美元，所有国家的法币的毛是美元，毕竟美元占全球的储备和支付的地位是核心地位，所以大家可以这样认为，也就是 70 年代之后， 70 年代之前，大家挂过黄金，黄挂过美元，美元挂过黄金， 30 年代的时候是大家直接挂钩黄金，对吧",
    "entities": [
      {
        "industry": "黄金",
        "level1": "行业自身情况",
        "level2": "对价物",
        "time_attr": "过去",
        "score": "1",
        "status": "挂钩美元",
        "doubt_remark": ""
      }
    ]
  },
  {
    "sentence": "那么现在其实大家挂钩美元不挂钩黄金，是现代的货币体系， 70 年代之后全球货币体系就是我们各家的",
    "entities": [
      {
        "industry": "黄金",
        "level1": "国家政策方向",
        "level2": "",
        "time_attr": "",
        "score": "",
        "status": "",
        "doubt_remark": ""
      }
    ]
  },
  {
    "sentence": "把 b 去挂钩美元，就相信美元的信用了，美元不挂钩黄金，那么所以从根本上来说，这轮黄金点涨是什么道理了",
    "entities": [
      {
        "industry": "黄金",
        "level1": "国家政策方向",
        "level2": "美元",
        "time_attr": "现在",
        "score": "2",
        "status": "不挂钩黄金",
        "doubt_remark": ""
      }
    ]
  },
  {
    "sentence": "很简单的把美元的信用下降了，美元的信用为什么会下降啊",
    "entities": [
      {
        "industry": "黄金",
        "level1": "国家政策方向",
        "level2": "美元",
        "time_attr": "现在",
        "score": "0",
        "status": "降价",
        "doubt_remark": ""
      }
    ]
  },
  {
    "sentence": "那个原因非常多，其实最关键的其实就是我们现在看到的，我们这一代人成长起来看到的是一个全球化的进程",
    "entities": [
      {
        "industry": "黄金",
        "level1": "国家政策方向",
        "level2": "全球化",
        "time_attr": "现在",
        "score": "",
        "status": "",
        "doubt_remark": ""
      }
    ]
  },
  {
    "sentence": "全球化进程代表什么",
    "entities": [
      {
        "industry": "黄金",
        "level1": "国家政策方向",
        "level2": "全球化",
        "time_attr": "",
        "score": "",
        "status": "",
        "doubt_remark": ""
      }
    ]
  },
  {
    "sentence": "全球 GDP 的生长、全球贸易的繁荣，那么在贸易的繁荣， GDP 的增长当中，大家想想看，我会需要更多的美元还是更少的美元啊",
    "entities": [
      {
        "industry": "黄金",
        "level1": "国家政策方向",
        "level2": "全球化",
        "time_attr": "现在",
        "score": "1",
        "status": "需要美元",
        "doubt_remark": ""
      }
    ]
  },
  {
    "sentence": "当然是更多的美元，对不对",
    "entities": [
      {
        "industry": "黄金",
        "level1": "",
        "level2": "",
        "time_attr": "",
        "score": "1",
        "status": "",
        "doubt_remark": ""
      }
    ]
  },
  {
    "sentence": "美元的信用，美元的地位会不断的加深的这个过程，那么在这个过程当中黄金就被压制了，那么好，现在我们看到的是百年未有之大变局，所谓的美元的信用被怎么样在逆全球化的过程当中，美元不光信用地位受到损失，美元的起用价值其实也在信用单",
    "entities": [
      {
        "industry": "黄金",
        "level1": "国家政策方向",
        "level2": "全球化",
        "time_attr": "现在",
        "score": "1",
        "status": "美元需求减少",
        "doubt_remark": ""
      }
    ]
  },
  {
    "sentence": "大家想想看，如果我在一个逆全球化的这样一个过程当中，在一个新能源革命，我不需要买那么多石铁、石油的这样一个过程当中，大家想想看我在全球支付当中其实我不再需要这么多美元了，那么在这个过程当中，既然美元不需要了，或者需要求篮减少了，那么长期被美元压制的黄金，那岂不就更值钱了啊",
    "entities": [
      {
        "industry": "黄金",
        "level1": "国家政策方向",
        "level2": "全球化",
        "time_attr": "现在",
        "score": "2",
        "status": "美元需求减少",
        "doubt_remark": ""
      }
    ]
  },
  {
    "sentence": "道理其实是非常简单的，这是根本原因，那么我们不说根本原因，我们再说说一个实际的原因，这个实际的原因可能大家也都可能大家有人提过，但是我在这里再强调一下，其实就是美元这一次大泛滥，印的太多钱的后遗症，后劲，哈哈，每一次这么多的美元，当时印了这么多钱，在那个新冠疫情期间，美国的通货膨胀达到了这么高的比例，史不起百二十年来最高的比例",
    "entities": [
      {
        "industry": "黄金",
        "level1": "国家政策方向",
        "level2": "美元",
        "time_attr": "过去",
        "score": "1",
        "status": "通货膨胀",
        "doubt_remark": ""
      }
    ]
  },
  {
    "sentence": "因为那么多钱，为什么当时美国的黄金没有啊",
    "entities": [
      {
        "industry": "黄金",
        "level1": "",
        "level2": "",
        "time_attr": "",
        "score": "",
        "status": "",
        "doubt_remark": ""
      }
    ]
  },
  {
    "sentence": "当时全球黄金没有涨，那么我告诉大家，根据历史上来看，黄金的涨幅其实都是怎么样",
    "entities": [
      {
        "industry": "黄金",
        "level1": "行业自身情况",
        "level2": "价格",
        "time_attr": "过去",
        "score": "",
        "status": "",
        "doubt_remark": ""
      }
    ]
  },
  {
    "sentence": "都是美元的后劲，也就是说美国上一轮通胀之后的 1- 2 年当中，黄金才会来到一个主推浪，这是一个后劲，也",
    "entities": [
      {
        "industry": "黄金",
        "level1": "国家政策方向",
        "level2": "美元",
        "time_attr": "始终",
        "score": "1",
        "status": "后于美元上涨",
        "doubt_remark": ""
      }
    ]
  },
  {
    "sentence": "就是从去年，哎货币",
    "entities": []
  },
  {
    "sentence": "超发的这样的后劲啊",
    "entities": []
  },
  {
    "sentence": "那么嗯，这个顺便提一下，当然我们中国的情况要好了很多，但是大家去看看4万亿也好，棚改也好，过去两年之后，当前一轮货币出现超发情况之下，那么后面确实会提升资产的价格的，对不对",
    "entities": [
      {
        "industry": "黄金",
        "level1": "国家政策方向",
        "level2": "货币超发",
        "time_attr": "过去",
        "score": "1",
        "status": "提升资产价格",
        "doubt_remark": ""
      }
    ]
  },
  {
    "sentence": "这一点其实全球都是一样的，货币银行权全球都是一样的",
    "entities": []
  },
  {
    "sentence": "那美元，大家可以认为美元是世界的央行，那当美元被超发之后，那么也一样的，它跑不了两年之后的后劲，嗯，那么前两轮的后劲是多少呢",
    "entities": [
      {
        "industry": "黄金",
        "level1": "行业自身情况",
        "level2": "美元",
        "time_attr": "过去",
        "score": "1",
        "status": "超发",
        "doubt_remark": ""
      }
    ]
  },
  {
    "sentence": "大家可以看一下在 Q1 one 和 Q1 two 当中近 20 年来的第一轮量化宽松，第二轮量化宽松当中，美元在超发之后的两年之后，黄金涨幅都在 75% 左右，那么这一轮美国是史无前例的超发了，它的怎么样",
    "entities": [
      {
        "industry": "黄金",
        "level1": "宏观市场",
        "level2": "量化宽松",
        "time_attr": "过去",
        "score": "1",
        "status": "美元超发",
        "doubt_remark": ""
      }
    ]
  },
  {
    "sentence": "它的美元的货币，那么后面所以黄金在一年到两年之后这一轮后劲所推动的黄金价格的涨幅是非常值得大家期待的啊",
    "entities": [
      {
        "industry": "黄金",
        "level1": "宏观市场",
        "level2": "量化宽松",
        "time_attr": "过去",
        "score": "1",
        "status": "美元超发",
        "doubt_remark": ""
      }
    ]
  },
  {
    "sentence": "其实逻辑，也就是这个逻辑，常见来看美国的，全球的这样的地位下降，美元怎么样",
    "entities": [
      {
        "industry": "黄金",
        "level1": "国家政策方向",
        "level2": "全球化",
        "time_attr": "现在",
        "score": "1",
        "status": "美元需求减少",
        "doubt_remark": ""
      }
    ]
  },
  {
    "sentence": "很道很简单道理吗",
    "entities": []
  },
  {
    "sentence": "美国原来国债这么值钱，只要怎么样",
    "entities": []
  },
  {
    "sentence": "只要 0.5% 甚至 0.25 的利率，全球央行抢着要",
    "entities": []
  },
  {
    "sentence": "现在美国国债多少钱啊",
    "entities": []
  },
  {
    "sentence": "美国国债要接近5%，对不对",
    "entities": []
  },
  {
    "sentence": "这么高的债代表了什么",
    "entities": []
  },
  {
    "sentence": "代表美元信用下降了",
    "entities": [
      {
        "industry": "黄金",
        "level1": "国家政策方向",
        "level2": "美元",
        "time_attr": "过去",
        "score": "1",
        "status": "信用下降",
        "doubt_remark": ""
      }
    ]
  },
  {
    "sentence": "大家买过美国国债，对不起，我现在再要买美国国债，要求你美元，给我百分之 5 块钱的美元，对不对",
    "entities": []
  },
  {
    "sentence": "我原来买美国所债，我觉得你信用特别好，我只要你 5 毛钱的美元",
    "entities": []
  },
  {
    "sentence": "现在怎么样",
    "entities": []
  },
  {
    "sentence": "全球买美国国债，我要你怎么样",
    "entities": []
  },
  {
    "sentence": "5 块钱的美元很简单的道理吗",
    "entities": []
  },
  {
    "sentence": "我不相信美国人了，不相信美元的信用货币地位了，不相信美国还能持续",
    "entities": [
      {
        "industry": "黄金",
        "level1": "国家政策方向",
        "level2": "美元",
        "time_attr": "现在",
        "score": "1",
        "status": "信用下降",
        "doubt_remark": ""
      }
    ]
  },
  {
    "sentence": "全球的什么呀",
    "entities": []
  },
  {
    "sentence": "全球的央行的地位了",
    "entities": []
  },
  {
    "sentence": "嗯，那么好啊，既然它不值钱了，那黄金就相对值钱了",
    "entities": []
  },
  {
    "sentence": "哈哈，这个这道理是很简单的，那么这实际上是远程逻辑，那么近期其实很简单，就是美元超发的后劲，其实在后这个后劲当中，大家不但看到了黄金的涨幅，其实大家也看看数字货币，包括比特币的涨幅，其实道理是一样的，其实都是因为怎样一轮货币超发之后对资产价格的推高，这是短期的原因",
    "entities": [
      {
        "industry": "黄金",
        "level1": "国家政策方向",
        "level2": "货币超发",
        "time_attr": "现在",
        "score": "1",
        "status": "提升资产价格",
        "doubt_remark": ""
      }
    ]
  },
  {
    "sentence": "希望我讲到了主要的一些原因啊",
    "entities": []
  },
  {
    "sentence": "对对对，还有什么",
    "entities": []
  },
  {
    "sentence": "还有一个现象，嗯，就是前段时间这个美元就是美联储它这个降息的预期其实又是往后推了，往后延迟了，然后当时市场上大家可能会觉得金价要回调，但是实际上其实走金价其实和这个每家利率走出了一样的，都是在往上走",
    "entities": [
      {
        "industry": "黄金",
        "level1": "国家政策方向",
        "level2": "美联储降息",
        "time_attr": "现在",
        "score": "1",
        "status": "预期后推",
        "doubt_remark": ""
      }
    ]
  },
  {
    "sentence": "这样的，对",
    "entities": []
  },
  {
    "sentence": "对对，所以您对这个观就这个看法有什么样的态度",
    "entities": []
  },
  {
    "sentence": "这个其实就是我刚刚说的嘛，其实我们现在面对的是一轮美元整体的全球央行的地位的这样一个重估",
    "entities": []
  },
  {
    "sentence": "嗯，每一次这样的重估其实都会带来黄金价格的这样的跃升",
    "entities": []
  },
  {
    "sentence": "大家要知道黄金价格有好几次跃升其实都来自于全球货币体系的这样一个变化，第一次最明显的就是当 30 年代之前，也就是 29 年全球金融危机之前，那么黄金是全球，是金本位的，嗯，这个时候黄金和美元是固定的，毛的，大概就是 15 美元每盎司的，黄金 15 美元每盎司，哎，到了怎么样",
    "entities": [
      {
        "industry": "黄金",
        "level1": "宏观市场",
        "level2": "金融危机",
        "time_attr": "过去",
        "score": "-1",
        "status": "之前是金本位",
        "doubt_remark": ""
      }
    ]
  },
  {
    "sentence": "29 年之后金本位怎么样",
    "entities": []
  },
  {
    "sentence": "破产了啊",
    "entities": []
  },
  {
    "sentence": "金本位破产了",
    "entities": []
  },
  {
    "sentence": "全球大萧条，金本位破产了",
    "entities": [
      {
        "industry": "黄金",
        "level1": "宏观市场",
        "level2": "全球大萧条",
        "time_attr": "过去",
        "score": "1",
        "status": "金本位破产",
        "doubt_remark": ""
      }
    ]
  },
  {
    "sentence": "原先的估值体系一下子崩坏了8万，一下子变成了 35 亿美元每盎司",
    "entities": []
  },
  {
    "sentence": "好的，到了下一轮是在什么时候并列定森林体系",
    "entities": [
      {
        "industry": "黄金",
        "level1": "国家政策方向",
        "level2": "布莱顿森林体系",
        "time_attr": "过去",
        "score": "",
        "status": "",
        "doubt_remark": ""
      }
    ]
  },
  {
    "sentence": "原来我们卯足了 35 美元每盎司这样一个当，怎么样",
    "entities": [
      {
        "industry": "黄金",
        "level1": "",
        "level2": "",
        "time_attr": "",
        "score": "",
        "status": "",
        "doubt_remark": ""
      }
    ]
  },
  {
    "sentence": "当第一次石油危机、第二次石油危机分别在 71 年和 73 年的时候发展，两次石油危机之后，美元怎么样挂钩不做黄金了",
    "entities": [
      {
        "industry": "黄金",
        "level1": "国家政策方向",
        "level2": "石油危机",
        "time_attr": "过去",
        "score": "1",
        "status": "美元不挂钩黄金",
        "doubt_remark": ""
      }
    ]
  },
  {
    "sentence": "全球货币体系出现重估了，这个时候怎么样",
    "entities": [
      {
        "industry": "黄金",
        "level1": "宏观市场",
        "level2": "全球货币体系",
        "time_attr": "过去",
        "score": "1",
        "status": "重新估值",
        "doubt_remark": ""
      }
    ]
  },
  {
    "sentence": "长期被压制了，真正压制 40 年的黄金梆一下跳起来，从 35 美元到多少",
    "entities": [
      {
        "industry": "黄金",
        "level1": "宏观市场",
        "level2": "全球货币体系",
        "time_attr": "现在",
        "score": "1",
        "status": "重新估值",
        "doubt_remark": ""
      }
    ]
  },
  {
    "sentence": "到 150- 200 美元，这么大的一个涨幅，下一次涨幅在哪里啊",
    "entities": [
      {
        "industry": "黄金",
        "level1": "",
        "level2": "",
        "time_attr": "",
        "score": "",
        "status": "",
        "doubt_remark": ""
      }
    ]
  },
  {
    "sentence": "在 911 事件 2000 年之后，原先的这样一个以美国为中心的体系受到了地缘种植的重大挑战",
    "entities": [
      {
        "industry": "黄金",
        "level1": "",
        "level2": "",
        "time_attr": "",
        "score": "",
        "status": "",
        "doubt_remark": ""
      }
    ]
  },
  {
    "sentence": "大家可以看一下美元从长，黄金从长期的 600 美元左右的这样一个宗旨绑起来调到了 1, 800 美元",
    "entities": []
  },
  {
    "sentence": "那么这一次我们又看到了一次全球货币体系的重估，全球央行体系的重估，也就是说美国这样一个或者美元这样一个超国家、超主权地位的货币，如果真正发生重估的话，那么我们看到的就是一轮被长期压制的这样一个黄金出现了它的一个估值反转或者估值回复啊",
    "entities": []
  },
  {
    "sentence": "大家千万不要以为是黄金涨了，即使我们从漫长的利息来看，其实不是涨的，而是黄金回到它原来的位置，它原先怎么样",
    "entities": []
  },
  {
    "sentence": "长期的又会这么会的，那我再解释一下，为什么我说了那么多年，说黄金是这样一种涨幅平台突破，那为什么是这样呢",
    "entities": []
  },
  {
    "sentence": "这不是我观察出来的，其实道理很简单的，当一个全球信用体系强大的时候，当一个世界央行体系怎么样啊",
    "entities": []
  },
  {
    "sentence": "以美国为中心或者以黄金为中心，它本身英国基金本物业中心的全球央行体系强劲的时候，那么政府信用是会压制黄金的，因为黄金是无限的，信用是有限的，你明白吗",
    "entities": []
  },
  {
    "sentence": "任何一个发行货币的国家一定会压制黄金的啊",
    "entities": []
  },
  {
    "sentence": "那么什么呢",
    "entities": []
  },
  {
    "sentence": "压不住了而已，为什么压制 30 年压不住导向下子",
    "entities": []
  },
  {
    "sentence": "压制 30 年压不住了，导向下子，这就是黄金的本质嘛",
    "entities": []
  },
  {
    "sentence": "所以大家看到黄金跟所有的铜吟旅孽全都不一样，为什么会这样的特征啊",
    "entities": []
  },
  {
    "sentence": "我相信别人，其实中国很少有人讲，但其实就是这个道理，就是全球信用体系维持了几十年维持不住了，当下的黄金回到它的本源又维持，不知道维持多少年，又维持不了当下的回到我们现在看到的是 100 年来第四次，可能全球央行体系，又或者说以美元为中心的全球主权货币体系可能维持不住了，所谓的北百年未有之大变局，那么在这种变局下，很简单的道理，我们看到了一个异常的现象，也就是说美元的信用在降低",
    "entities": []
  },
  {
    "sentence": "而怎么样美元信用降低就是美债利率在升高，明白了吗啊",
    "entities": []
  },
  {
    "sentence": "而黄金也在降，这逻辑就很顺嘛",
    "entities": []
  },
  {
    "sentence": "嗯，所以说他们俩可能不是之前我们想的那种一个，对",
    "entities": []
  },
  {
    "sentence": "在前面的两年当中，在前面的 20 年当中你说的这个关系是存在的，因为我们在一个稳定态当中，就平台期当中，平台词，哎，平台期当中我们应该怎么看",
    "entities": []
  },
  {
    "sentence": "黄金是一种无息资产，美元是一种有息资产，美债是一种有息资产",
    "entities": []
  },
  {
    "sentence": "美国的债券怎么样",
    "entities": []
  },
  {
    "sentence": "值钱了，那么黄金不值钱了，美国的债券不值钱了，黄金值钱了",
    "entities": []
  },
  {
    "sentence": "这是一个稳定期的估值，平平大局就这么估，对，平平大局就这么估",
    "entities": []
  },
  {
    "sentence": "但是怎么样",
    "entities": []
  },
  {
    "sentence": "当这个平台打破之后，那么原先的破折体系，二十年来所有的估值体系，包括去年年底中国所有的有色研究员都研究错了什么道理，因为他们漫长的研究生涯当中，没有看到一支平台去被打破而已",
    "entities": []
  },
  {
    "sentence": "是的，那可能我们平台期的时候，他们还是以两种资产这样的关系来进行对比，当然这种跃升期，可能",
    "entities": []
  },
  {
    "sentence": "跃升期黄金要重新定价，也就是说过去 20 年对黄金的压制的束缚，也就是主权信用对它的压制的束缚怎么样",
    "entities": []
  },
  {
    "sentence": "被打破了",
    "entities": []
  },
  {
    "sentence": "嗯，他要跳到一个新的平台上进行这样一个新的平衡，我并不认为，哈哈，我并不认为美元又完蛋了，我也不认为",
    "entities": []
  },
  {
    "sentence": "世界贸易怎么样，就不大家不贸易了，只是怎么样在一个新的平台上达到新的平衡",
    "entities": []
  },
  {
    "sentence": "那么在这个过程当中，原先 20 年对黄金的压制怎么样",
    "entities": []
  },
  {
    "sentence": "这样一个主权信用的压制被打破了，嗯，那么黄金会行到他自己新的这样一个稳定性的平台",
    "entities": []
  },
  {
    "sentence": "嗯，好的，好的，感谢这个张总，对这个均价，对我们这个黄金非常深刻的一个理解，无论是长期的还是短期的原因，不知道大家有没有什么疑问啊",
    "entities": []
  },
  {
    "sentence": "我看到有一个人问，说想听听张总讲一下国际形势对于这个均价的这样的一个影响，您觉得这个国际形势的因素重要吗",
    "entities": []
  },
  {
    "sentence": "就，唉，这个问题我觉得非常好，这位小伙伴非常专业，因为大家都说嘛，我也就说黄金乱是藏黄金，甚是藏古董，黄金是用来避险的，对，是",
    "entities": []
  },
  {
    "sentence": "买黄金",
    "entities": []
  },
  {
    "sentence": "但是但如果细心的小伙伴真的去研究这件事情，大家会发现其实很多地缘政治事件，它其实只是对黄金价格形成微了，它最终不决定黄金的走势，非常有意思",
    "entities": []
  },
  {
    "sentence": "前一段时间我可以介绍一下，有一位机构投资者问我，张总，那个以色列撤兵了，那么是不是黄金要跌下去了",
    "entities": []
  },
  {
    "sentence": "嗯，那么我跟他说是怎么说的",
    "entities": []
  },
  {
    "sentence": "我回答就是当年黄金涨起来，你记得吗",
    "entities": []
  },
  {
    "sentence": "是不是因为以色列进兵",
    "entities": []
  },
  {
    "sentence": "如果以色列进并没了黄金涨起来，那么凭什么以色列测病黄金就要会跌下去",
    "entities": []
  },
  {
    "sentence": "是不是这个道理啊",
    "entities": []
  },
  {
    "sentence": "非常简单的道理，这一些地缘政治事件，不管是袈裟冲突，还是所谓的胡塞武装开炮，或者说伊朗袭击，那个我对其打击什么地方啊",
    "entities": []
  },
  {
    "sentence": "这一些对黄金有影响吗",
    "entities": []
  },
  {
    "sentence": "当然有影响，但它都是短期世界，它都是在一个大趋势上的微老向，我们的黄金的中长期走势并不会因为这一些短期事件而发生改变",
    "entities": []
  },
  {
    "sentence": "当然交易性机会是有的，大家如果只预先知道某个武装开炮，那你买一点，那个大概率是涨的，但是这跟事情平息之后，它还是会跌到那个长期曲线上的，这一点是没有问题的",
    "entities": []
  },
  {
    "sentence": "那么我是不是自己打理啊",
    "entities": []
  },
  {
    "sentence": "我一直说到黄金是世界上怎么样最好的避险资产，那为什么说地缘政治冲突",
    "entities": []
  },
  {
    "sentence": "其实对他只是微老向啊",
    "entities": []
  },
  {
    "sentence": "一定要结合我对第一个问题的分析，你这个地缘政治事件是不是构成了对美元或者对全球主权货币体系的挑战",
    "entities": []
  },
  {
    "sentence": "如果你这个地缘政治事件是构成了对全球主权货币体系的挑战，对全球 GD 缘、全球信用体系达成了挑战这个水平，那么你就会深刻的本质的影响竞价",
    "entities": []
  },
  {
    "sentence": "如果你这个地缘政治事件不构成对全球货币体系的重估，不构成对全球主权信用体系的挑战，那么你这个所谓的地缘冲突事件，那么对黄金没有根本性的影响，顶多会有交易性的机会啊",
    "entities": []
  },
  {
    "sentence": "交易性机会肯定是有的啊",
    "entities": []
  },
  {
    "sentence": "对，我刚刚说到了，你如果预知那个哈，呵呵，原来和平的地方突然怎么样",
    "entities": []
  },
  {
    "sentence": "发生冲突了，那么黄金在短期可能会涨个一段时间，那是肯定有的，当然这个大家无法预知，我是一点情报都没有，对吧",
    "entities": []
  },
  {
    "sentence": "但是从增长期来看其实没有的，那么我举个刚刚在说到这些，我刚刚其实已经举过两个例子了",
    "entities": []
  },
  {
    "sentence": "什么叫对全球地缘政治，或者对全球怎么样",
    "entities": []
  },
  {
    "sentence": "不是地缘政治啊",
    "entities": []
  },
  {
    "sentence": "什么叫地缘政治",
    "entities": []
  },
  {
    "sentence": "事件",
    "entities": []
  },
  {
    "sentence": "对全球货币体系，对全球主权信用体系造成冲击的很简单，大家去看看 71 年和 73 年的两次石油危机，中东战争之后，为了反制阿拉伯国家，为了反制美国，形成了欧佩克",
    "entities": []
  },
  {
    "sentence": "怎么样将石油的价格大幅的提升，在这个过程当中造成了美元地位的下降，造成了布雷顿森林体系的破产啊",
    "entities": []
  },
  {
    "sentence": "简单的一次，第一次 COEG 和第二次 COEG 就是典型的地缘政治事件，但是它造成了严重的后果",
    "entities": []
  },
  {
    "sentence": "造成了什么",
    "entities": []
  },
  {
    "sentence": "造成了布雷顿森林体系的破产，造成了美国全球货币地位的下降",
    "entities": []
  },
  {
    "sentence": "造成了怎样",
    "entities": []
  },
  {
    "sentence": "造成了全球主权货币系统的重估",
    "entities": []
  },
  {
    "sentence": "哎，那个时候怎么样",
    "entities": []
  },
  {
    "sentence": "黄金 35 美元变成了 150 美元，黄金是会受到地缘政治冲击的，但是对不起，小打小闹冲击不了我",
    "entities": []
  },
  {
    "sentence": "但是如果你真正的冲击了全球法定货币信用货币低位的话，整个体系如果被你这个地缘政治冲击的话，那么它就会造成深远的影响，这就是个非常典型的事件，小一点来说就是 911 事件， 911 事件也是一个典型的地缘政治事件，但是它确实也改变了当时美国在全球的这样一个地位，那么最终造成了这样一个黄金价格的重股，也在一定程度上也会造成",
    "entities": []
  },
  {
    "sentence": "当然它的影响之深刻，肯定是不如两次石油危机的，也就是说大家去看看，如果大家再碰到了两次石油危机，中东战争引起了第四次中东战争引起的两次石油危机，造成了 29 年、 31 年的这种全球大萧条，如果大家再碰到 911 这种事件，这种级别的全球地缘甚至事件，而这种甚源甚至事件正好会冲击美元的地位的话，那么大家可以认为这种事件确实会影响到黄金的定价，其他的事件在中长期来说对黄金定价其实没有影响",
    "entities": []
  },
  {
    "sentence": "好的好的，不知道有没有解答这位朋友的这个疑惑啊",
    "entities": []
  },
  {
    "sentence": "就是说这个电源冲突其实它也是分等级的，分这个它这个影响深不深厚，我们可以看一下，如果有一个 DN 冲突，大家可以想一下，你觉得这个对于咱们这个美元体系会不会造成一个冲击",
    "entities": []
  },
  {
    "sentence": "对现在的全球的这个信用体系会不会造成冲击",
    "entities": []
  },
  {
    "sentence": "那如果造成冲击，它可能会对后面的金价长期走势会有一定的影响，但是其实有很多的地缘冲突，可能他就是打仗，是不是这种可能",
    "entities": []
  },
  {
    "sentence": "就是可能会短期的会有一些波动，对他可能是对",
    "entities": []
  },
  {
    "sentence": "中长期其实是没有影响",
    "entities": []
  },
  {
    "sentence": "的，就是我们统计学校学的那个最后的那个谬，对吧",
    "entities": []
  },
  {
    "sentence": "哈哈，那个干扰",
    "entities": []
  },
  {
    "sentence": "是会被消掉的，因为刚才说了，你既然要进兵，你自然要撤兵，那么最终你不是抵消掉了吗",
    "entities": []
  },
  {
    "sentence": "是的，好的，那我们看到还有朋友在问说您这个管理的这个基金，您管理基金是黄金股ETF，嗯，那黄金股和黄金它们之间有什么样的关系",
    "entities": []
  },
  {
    "sentence": "可能咱们前面讲都是这个实物黄金的一个金价，嗯，那在现在这个时间点上我们是怎么样去选择投资黄金的",
    "entities": []
  },
  {
    "sentence": "一些投资标的会比较",
    "entities": []
  },
  {
    "sentence": "好",
    "entities": []
  },
  {
    "sentence": "非常好，这个问题非常好，因为我是我这个做黄金做了好多年，那个关注黄金 600 美元，我 UF 的时候我就关注黄金了，后来在国泰是做了中国第一批的黄金ETF，然后到供应瑞幸又做了一个黄金ETF，到永银做了黄金股ETF",
    "entities": []
  },
  {
    "sentence": "这个，嗯，到哪里",
    "entities": []
  },
  {
    "sentence": "我做个黄金，因为我对黄金一直是觉得就是这是我最底线的逻辑，跟大家分享一下，就是我在过去的几十几年当中，一直觉得黄金被低估了，嗯，受到了美元过分的压制，这是我的一个投资的一个底线逻辑，而且这个逻辑一直是没有变的，现在可能是这个逻辑兑现的时候",
    "entities": []
  },
  {
    "sentence": "现在正好在兑现这个逻辑的时候有问题了",
    "entities": []
  },
  {
    "sentence": "就是，然后就是也不是终于到了，其实黄金其实一直在涨，只是就是没有那个那种爆发性的，那个刚刚开始爆发性的",
    "entities": []
  },
  {
    "sentence": "其实那这十几年来，其实黄金的宋新其实是在往上的，这没有问题啊",
    "entities": []
  },
  {
    "sentence": "然后其实刚刚这个问题提得非常好，就是普通人比如说我们有黄金ETF，有黄金股ETF，有各种各样的黄金投资工具，究竟什么啊",
    "entities": []
  },
  {
    "sentence": "适合哪一种投资人群，对吧",
    "entities": []
  },
  {
    "sentence": "这个问题我觉得很本质吗啊",
    "entities": []
  },
  {
    "sentence": "其实我是觉得根据大家的风险偏好不一样，其实每一种投资工具都是有它的市场的啊",
    "entities": []
  },
  {
    "sentence": "嗯，就看你自己的那个风险收益偏好了",
    "entities": []
  },
  {
    "sentence": "如果你是一个非常保守的人，其实我是非常",
    "entities": []
  },
  {
    "sentence": "嗯，建议大家就买我们后面背景这一种食物金条的，食物金条，其实食物黄金，因为金条不指的是金条，只是关投资金条",
    "entities": []
  },
  {
    "sentence": "我不说消费品，我只说投资金条啊",
    "entities": []
  },
  {
    "sentence": "因为投资金调的流动性非常好，哪里都会收，都会回收，我们做投资的不光要考虑到买，一定要考虑到卖，要有流动性啊",
    "entities": []
  },
  {
    "sentence": "上次不是我在这个演播室里，人家还问我，那你囤好多好多茅台酒，行不行",
    "entities": []
  },
  {
    "sentence": "唉，看上去账面很富贵，但是说句老实话，你要卖这些有点难度的，对吧",
    "entities": []
  },
  {
    "sentence": "但黄金没有难度，只要你是真的黄金，那回收是没有难度的",
    "entities": []
  },
  {
    "sentence": "那么我买的时候加价大概 10 块钱每克，那卖的时候再加价 10 块钱每克，也就是我会承担 20 元人民币每克的这样一个交易成本，那么其他升值收益都是我的了啊",
    "entities": []
  },
  {
    "sentence": "所以其实如果黄金是一个对于很多投资者来说其实是最稳妥、最保守的这样一种投资方式，对吧",
    "entities": []
  },
  {
    "sentence": "虽然它交易成本高一点，但是确实是真金白银，拿在手里安全感，哈哈哈，安全感最高，对吧",
    "entities": []
  },
  {
    "sentence": "这个对于普通人当然是这样，那投资还需要安全感的，对吧",
    "entities": []
  },
  {
    "sentence": "你买一个看不见、摸不着的东西跟你买，跟金条放在家里，你老婆对你的评价是不同的，哈哈哈啊",
    "entities": []
  },
  {
    "sentence": "这是黄金，但是在实物黄金的时候以上，那么大家如果我要继续降低我的交易成本，继续提高我的流动性和攻击力，那么大家就考虑考虑在银行端，比如说纸黄金基存金，在我们的二级市场，比如说黄金ETF，另一个我会进一步的增加了我的这样一点点的流动性和进攻性，也就是说我可以换手率更高了，你买 15 黄金和换手率不会太高的，对不对",
    "entities": []
  },
  {
    "sentence": "你不大可能买一根金条，过两个礼拜我就去卖掉",
    "entities": []
  },
  {
    "sentence": "哈哈哈，不太可能的，对吧",
    "entities": []
  },
  {
    "sentence": "你会降低你的流动性的，所以说 15 金条可能是一个最保守的投资，那么你要这样加减进攻性，我说的像银行端的几成金基成金二级市场的什么呢",
    "entities": []
  },
  {
    "sentence": "那个黄金 ETF 其实都是不错的选择",
    "entities": []
  },
  {
    "sentence": "嗯，它的特征就是黄金，全球黄金涨一块钱，你这个东西也涨一块钱，它是同步的，没有杠杆的，是同步的，斜率是一模一样的",
    "entities": []
  },
  {
    "sentence": "然后流动性也是比较好的，基本上不管你在银行买卖的时候，还是在二级市场买卖的时候，基本上它的交易成本是要远远低于两 20 块每克的，对不对啊",
    "entities": []
  },
  {
    "sentence": "我们你买金条，你的交易成本是 20 块钱每课，那么这一些它的成本是远远低于的，所以适合大家做更加频繁的这些交易，对吧",
    "entities": []
  },
  {
    "sentence": "进攻性就会更强一点，那么我们的黄金股ETF，那就是一种进攻性更强的资产，为什么道理",
    "entities": []
  },
  {
    "sentence": "根据历史上的这样一个分析，我黄金股在过去 20 年来，那么过去十年来在上涨的时候，它大概的这个贝塔也就是涨幅是 1.5 倍，也就是说黄金涨一块钱的话，黄金股大概能涨 1.5 倍一块五，那么黄金下跌的时候，当然了黄金股跌的也是比较多，大概是 1.3 倍左右，这么这个在中国也是成立的，在英国、美国的市场上也是成立的，也就是说黄金股对黄金是有一定的放大作用",
    "entities": []
  },
  {
    "sentence": "所以我到友谊来赶紧发一个黄金股，因为我觉得黄金要涨了，哈哈哈，对吧",
    "entities": []
  },
  {
    "sentence": "在涨的时候，那么黄金股 ETF 可以比黄金 ETF 给大家获得更多的，你这个对黄金判断正确带来的回报，对不对",
    "entities": []
  },
  {
    "sentence": "这就是一个回报的这样一个放大器",
    "entities": []
  },
  {
    "sentence": "当然了，这里也要提醒大家，如果黄金下跌的时候，那么黄金股的跌幅也是会超过黄金的，但上涨的时候，那么黄金股的进攻性它的收益是超过黄金的，这是更进，更更具有进取心的这些投资者，那么最有进取心的，或者最具有投资经验的，那你可以考虑上期所的黄金期货合约，考虑 t 加d，这重金所的 t 加d，那么这个其实我个人是不太建议投资的，为什么",
    "entities": []
  },
  {
    "sentence": "道理不是因为觉得大家看不准黄金的机会，其实主要因为那种跟我们原先我前面想的三种都不一样，这些投资就是保证金交易的，是杠杆交易的，那么杠杆交易的投资者有时候即使你看对了，由于你的保证金管理的问题，也会爆仓",
    "entities": []
  },
  {
    "sentence": "哈哈，这个很多了，这个我就不多说，因为",
    "entities": []
  },
  {
    "sentence": "不建议大家",
    "entities": []
  },
  {
    "sentence": "不太建议，因为对于普通人来说，我觉得没有必要去加杠杆去做这样一个很激进的投资",
    "entities": []
  },
  {
    "sentence": "对，因为加杠杆之后你设提到了盯盘，就你买黄金股也好，买黄金 ETF 也好，其实你是不用盯盘的，嗯，对吧",
    "entities": []
  },
  {
    "sentence": "每天看个收盘价就可以，对吧",
    "entities": []
  },
  {
    "sentence": "它涨多少跌多少会体现你的净值上，但那个期货可不一样，期货跟你盯盘是有关的，对吧",
    "entities": []
  },
  {
    "sentence": "你说我买了一个多头，晚上一看涨了，但不见得",
    "entities": []
  },
  {
    "sentence": "他说如果跌下去，再涨起来之后可能你已经爆仓了，涨幅跟你没关了，对不对",
    "entities": []
  },
  {
    "sentence": "你得盯着他来的，但跌下去之后你还得补保证金，所以那个可能不太适合普通人做啊",
    "entities": []
  },
  {
    "sentence": "嗯，所以，嗯，我再讲一遍，就是我认为在这一轮黄金行情当中，大家可以参与的这些过程，一个就是最稳妥的保持着，那么你买点金条，对吧啊",
    "entities": []
  },
  {
    "sentence": "激进一点的，希望取得一些流动性和进攻性的，那么黄金 ETF 或者银行的计算金之类的，那么最那个希望就是将我们的投资的判断正确的投，各位正确的投资判断，对，黄金正确的投资判断变成一个很具，就变成放大，能够放大这块投资判断的收益的，那么黄金股 ETF 是适合大家的，毕竟我说黄金是坐右侧的， 20 年来， 20 年一轮的这样一个突破的机会，对吧",
    "entities": []
  },
  {
    "sentence": "每个人那个生命当中可能没有几次看到黄金股的这种黄金本身的这样一个美元体系，重估下黄金的一个大幅的这样一个突破的机会，如果大家看到这样的机会的话，其实想要利用这一种机会的话，那么黄金股是一个非常好的这样一个放大器的这样一个作用，放大器的这样作用，最后我也强调一下，就是有一些威胁小伙伴买的是那种，就是叫啥",
    "entities": []
  },
  {
    "sentence": "金豆我不知道，你知道吗",
    "entities": []
  },
  {
    "sentence": "金豆我知道",
    "entities": []
  },
  {
    "sentence": "那个其实作为收藏品或作为装饰品可以，那应该",
    "entities": []
  },
  {
    "sentence": "但是的那个不太适合这个，当然每个人那个偏好不同，但是我只是提醒大家一下，从一个基金经理的角度，从投资品的角度，他可能不太适合投资啊",
    "entities": []
  },
  {
    "sentence": "为什么",
    "entities": []
  },
  {
    "sentence": "道理基础金价现在 550 亿克，对吧",
    "entities": []
  },
  {
    "sentence": "银行那个你如果去买投资金条的话， 560 一克， 560 一克，这我就说普通情况，那么你卖掉的话，那么在多十块钱的这样一个手续费，是这样的一个情况",
    "entities": []
  },
  {
    "sentence": "但是你如果是金，你买金首饰、金镯子的话大概 720 一克，现在那么你可能买金豆的话也要 600 多一克，那么你这个 600 多一克，你买来的时候加价了 100 块钱",
    "entities": []
  },
  {
    "sentence": "那你卖出的时候其实不加价还是550，也就是说这种投资品千万大家要注意，就是如果大家真的是从投资角度来看的话，那么实物金就是那种投资金条，可能是最简单的，因为它手续费成本是最低的，不管它造成什么形状，其实这个手续费都是很高的",
    "entities": []
  },
  {
    "sentence": "然后你如果你要卖出去的话，那么回收其实不会在乎你的形状，只看客诉",
    "entities": []
  },
  {
    "sentence": "嗯，所以如果大家想要不是每天一点、每每什么，每个月一点小幸福过稳稳的投资，那其实还是金条比较好啊",
    "entities": []
  },
  {
    "sentence": "嗯，那个金豆可能不太适合这个投资性需，当然了，你的装饰新需求，你的那个收藏新需求，那个满足你，其实我觉得也是可以的，对吧",
    "entities": []
  },
  {
    "sentence": "而且如果金豆，如果你拿很久很久很久还是会有一定的收益的",
    "entities": []
  },
  {
    "sentence": "是有收益的收益，我是觉得要不我们从来没说收益的问题",
    "entities": []
  },
  {
    "sentence": "金条的收益要低一点",
    "entities": []
  },
  {
    "sentence": "收益我肯定觉得没问题啊",
    "entities": []
  },
  {
    "sentence": "这个给咱，因为我是基金经理，肯定是从收益最大化的角度来考虑一个问题，收益当然会有了，这个是我，我觉得",
    "entities": []
  },
  {
    "sentence": "很多模式成本也不加工的成本算到我",
    "entities": []
  },
  {
    "sentence": "你说比如说几年前你买了个大金镯子，那现在收益好高了，对吧",
    "entities": []
  },
  {
    "sentence": "这个是肯定的，这个一样的上涨是一样上涨，只是就是你付在上面这些加工费你是收不回来的，对，在你卖出的时候是收不回来的",
    "entities": []
  },
  {
    "sentence": "对",
    "entities": []
  },
  {
    "sentence": "食物黄金其实还有一个叫鞋底成本",
    "entities": []
  },
  {
    "sentence": "对吧",
    "entities": []
  },
  {
    "sentence": "什么",
    "entities": []
  },
  {
    "sentence": "什么鞋底成本",
    "entities": []
  },
  {
    "sentence": "什么叫鞋底",
    "entities": []
  },
  {
    "sentence": "成本",
    "entities": []
  },
  {
    "sentence": "整体成本",
    "entities": []
  },
  {
    "sentence": "就是之前上那个经济课的时候说，就是你要去频繁的去存钱或者是去取钱，然后因为他通胀的时候的当时创出来这样，然后我们如果去实物的话，你要去换黄金，然后去买黄金，再去卖黄金，其实这个还是有鞋底成本，那请投资我们二级市场啊",
    "entities": []
  },
  {
    "sentence": "对，去买这个 ETF 的话，其实是省了你这部分的时间",
    "entities": []
  },
  {
    "sentence": "对，因为确实就是各家金店的这个金条的款式是不一样的，有很多金店只收，包括银行，他只收自己银行的那个发出来的金条，对吧",
    "entities": []
  },
  {
    "sentence": "其实其他的金条他可能是互相也不认的，对吧",
    "entities": []
  },
  {
    "sentence": "不像我们的这个 ETF 份额，那你每个银行都认，对吧",
    "entities": []
  },
  {
    "sentence": "对，这个就是就这种东西其实它的统一性来说，肯定是二级市场的投资工具，统一性更高一些",
    "entities": []
  },
  {
    "sentence": "对",
    "entities": []
  },
  {
    "sentence": "对对，还是这种产品更有这个同",
    "entities": []
  },
  {
    "sentence": "质化嘛",
    "entities": []
  },
  {
    "sentence": "对",
    "entities": []
  },
  {
    "sentence": "好的",
    "entities": []
  },
  {
    "sentence": "然后我还看到这个有朋友在问，说觉得现在可能几年前就已经开始在买黄金了，嗯，然后到现在已经低了，一定会涨幅，然后但是现在看着黄金好像还在涨的这样的趋势中，然后就也想问问我们经理，您觉得现在是一个上车的好时机，还是说我已经可以就是止盈了这样的一个",
    "entities": []
  },
  {
    "sentence": "那就可能我因为我不知道您的资产配置这个东西跟你资产配置是有关的，如果你的资产配置当中本来就是全仓黄金的，那么涨那么多了",
    "entities": []
  },
  {
    "sentence": "我相信兑现一些收益其实是可以的，那其实没有什么问题，但是即使兑现收益，我也建议这位小伙伴保留手上的黄金，保留手上黄金的头寸啊",
    "entities": []
  },
  {
    "sentence": "在任何一个时间上，其实我相信投资者都应该保留黄金的头寸，我还是我特别喜欢尹达利奥的那句话，我们最有名的基金经理之一，我们的前辈，美国的基金经理达利奥",
    "entities": []
  },
  {
    "sentence": "他一直说这样一句话，如果大家在投资组合当中没有黄金的话，说明你怎么样",
    "entities": []
  },
  {
    "sentence": "既不懂经济学，也不懂历史学，哈哈哈，也就是说在任何一个情况下，大家都应该去配置一点黄金的头寸",
    "entities": []
  },
  {
    "sentence": "因为黄金投诉有两个极端的作用，一个就是极端抗通胀，第二个就是极端避风险，这两个头，这两个功效是其他任何的这样一资产配置做不到的",
    "entities": []
  },
  {
    "sentence": "所以你不管怎样去构制你的资产组合，这个无所谓，跟大家的风险偏好有关，不管你怎样构筑你的市场配置组合，那么我作为看了十几年黄金的人告诉大家，不管怎么样去构渡这个组合，但是在这个组合当中大家一定要持有一点的黄金资产作为底仓，这个我相信你不辜负黄金，黄金也不会辜负",
    "entities": []
  },
  {
    "sentence": "你",
    "entities": []
  },
  {
    "sentence": "嗯，好的好的，刚才已经讲了很多关于这个金价的一个催化的因素",
    "entities": []
  },
  {
    "sentence": "那可能我们前面是复盘了之前能够造成我们这一波增加上涨这样的因素，那还想问的就是您觉得就是目前刚才提到的远远近近大大小小的因素，后续会有什么样的变化吗",
    "entities": []
  },
  {
    "sentence": "我们遇到什么样的情况，我们就觉得，噢，那这里的跃升期可能已经快接近一个问题",
    "entities": []
  },
  {
    "sentence": "了，这个其实本身这个跃升期它也是一个漫长的历史演化的这样一个过程啊",
    "entities": []
  },
  {
    "sentence": "美元的这样一个扩张周期伴随着全球化的进程，我刚刚已经说到了这一轮美元的整个扩张周期代表着美新能源革命和第四次科技、第四次信息革命之后，这样一个全球化的这样一个进程，用美元的地方越来越多，对不对啊",
    "entities": []
  },
  {
    "sentence": "这是一个美元的这样一个根本，那么现在这个去美元化的这样一个过程，美元信用下降，然后美债存隐含着危机，这一些也是一个非常漫长的这样一个历史过程，所以这个过程正在进行当中",
    "entities": []
  },
  {
    "sentence": "所以我一再说黄金是做右侧的，其实你前面其实不用去赌，美国会破产，但是现在我也不认为美国会破产，它只是有这么一个趋势而已，对吧",
    "entities": []
  },
  {
    "sentence": "会把什么下调美国信用评级，这是唯一美元评分，只是没有那么强势，但是即使这样一个过程，它也是一个缓慢的这样过程，所以它会去配合着黄金的这样一轮，这样一个右侧的这样一个行情，所以我们在目前来看其实是看不到整个这样一个过程被扭转的，这个扭转我觉得很难，这个过程的扭转是很难，毕竟前面美国超发了这么多，对不对啊",
    "entities": []
  },
  {
    "sentence": "毕竟现在去全活化的过程确实是在进行当中",
    "entities": []
  },
  {
    "sentence": "毕竟在新能源革命之后，石油美元之矛松动了，这一些其实都是很根本的东西",
    "entities": []
  },
  {
    "sentence": "对不起，非常非常根本的东西， 20 年前我们还没看到，甚至十年之前我们都没看到我们有什么，有新能源车，对吧",
    "entities": []
  },
  {
    "sentence": "我们现在路上全是新能源车，大家看看我们中国的伟大发，可以说是伟大奇迹，在路上全是新能源车，其实这个也是对美元霸权的动摇有一个很重要的作用，因为美元阵芒，海外美元阵芒是石油美元，如果石油的用量没有必须那么大的话，直接对美元",
    "entities": []
  },
  {
    "sentence": "所以不管从政治上还是技术上，这一轮美元的这样一个衰落，或者说美国全球法定货币地位的这样一个下降，其实它本身就是过去 20 年来各种各样事件的一个综合的结果，所以并不是某一件事情造成的，是很多事件综合的这样一个结果",
    "entities": []
  },
  {
    "sentence": "那你说你要让他重新扭转回来，或者是那可能要我们拭目以待吧",
    "entities": []
  },
  {
    "sentence": "嗯，那可能有一些很大的这样一个事件，否则的话我是会认为黄金会在后面找到他新的应该对美元的平衡点的，现在",
    "entities": []
  },
  {
    "sentence": "还没有到平衡点的前面，其实都可能会是一个上升这样的趋势，对",
    "entities": []
  },
  {
    "sentence": "趋势没有变，就是原先的这些驱动因素，其实我们，嗯，因为这些驱动因素都是，其实都是长周期的和，而且是非常深刻的，甚至涉及到人类的信源革命，对吧哈",
    "entities": []
  },
  {
    "sentence": "这一些，其实这个这种过程既然没有结束的话，那你怎么能看到它到底了呢",
    "entities": []
  },
  {
    "sentence": "对对对，那这也回答了这个朋友，这个朋友说的是黄金投资的最佳时机是什么时候",
    "entities": []
  },
  {
    "sentence": "刚才张总也讲投资黄金其实可以走右侧进行布局，那目前其实就是这个黄金正在上涨的这样的一个",
    "entities": []
  },
  {
    "sentence": "右侧，一个非常难得的右侧，大家其实在整个投资生意当中是很少见到黄金真正的右侧的，那么这一次其实是一个右侧性的机会，是一个技术性",
    "entities": []
  },
  {
    "sentence": "机",
    "entities": []
  },
  {
    "sentence": "好的，那我们这次继续聊我们的黄金股产品，那我们黄金股产品刚才也提到了它是一个放大器的这样的一个效果，刚才张总有提到，就是说它会更有进攻性",
    "entities": []
  },
  {
    "sentence": "那这边其实我有一些数据做补充，就是从我们拉长到从现在到半年前，我们这半年的时间黄金股指数累计上涨的涨幅是 32 个点，然后同期这个伦敦金的上涨幅度是 25 个点",
    "entities": []
  },
  {
    "sentence": "那我们再拉上看，从 20220 年到现在，上海已经上涨了 58 个点，但是黄金股上涨了 81 个点",
    "entities": []
  },
  {
    "sentence": "对，我们能看到其实它是有一个很明显的，这样在上涨期会有一个超额的这样的一个放大作用的",
    "entities": []
  },
  {
    "sentence": "对，那也想请张总来聊一聊，就觉得这个他们之间为什么会存在这样的一种上涨的一个弹性",
    "entities": []
  },
  {
    "sentence": "以及我们黄金股和黄金它们之间会有什么样的一个区别啊",
    "entities": []
  },
  {
    "sentence": "除了在这个超额收益方面",
    "entities": []
  },
  {
    "sentence": "这个非常好，您这个问题提得非常好，因为我在这个好像我也回答过几次，嗯，那么我再总结一下黄金股为什么去放大黄金啊",
    "entities": []
  },
  {
    "sentence": "当然刚才我们的主持人报了一串数据，差不多也就是 1.5 倍的这样一个放大是比例，为什么在中国是这样，在美国、英国也是这样啊",
    "entities": []
  },
  {
    "sentence": "它究竟是我们从光看图总结出来一个经验公式，还是它背后有真正的经济学或者金融学的本质",
    "entities": []
  },
  {
    "sentence": "那么我告诉大家，它确实是有金融学和经济学意义的啊",
    "entities": []
  },
  {
    "sentence": "黄金股对黄金的放大作用，因为我们去投资股票，其实投资的是什么",
    "entities": []
  },
  {
    "sentence": "投资的是这家企业，对不对",
    "entities": []
  },
  {
    "sentence": "唉，这家企业怎么样啊",
    "entities": []
  },
  {
    "sentence": "相当于拆成了很多份额，我们每个人去持有了这个份额，相当于做了这个企业的主人，对吧",
    "entities": []
  },
  {
    "sentence": "那么这个企业盈利情况的改善，它未来的利润就代表着我的股价的增长",
    "entities": []
  },
  {
    "sentence": "大家一定要这个角度来看待这个问题，我投资的一家金矿企业，因为我不能提名字，我投资的这家金矿企业大家要记住并不是投资他的黄金，而是投资这家企业的盈利能力，这个一定要记住，并不是投资这家企业有多少金子，每个企业算下净值多少，那我投不到，不是这样，其实是投资这家企业的盈利能力，那么盈利能力我们就要看它的资产负债表，对于一家金矿企业的资产负债表它是怎么样的",
    "entities": []
  },
  {
    "sentence": "它的负，它的那个资产端究竟是什么",
    "entities": []
  },
  {
    "sentence": "那么我告诉大家，它的资产端不是黄金，如果是黄金的话，它的资它就变成了一家怎么样黄金的销售企业了，对不对",
    "entities": []
  },
  {
    "sentence": "金子都挖出来了，它的金子没有挖出来，金子还有意向，所以它的资产负债表的基某，比如说某某金矿、某某黄金，它本身的这样一个资产负债表的资产端，它并不是黄金，而是什么呢",
    "entities": []
  },
  {
    "sentence": "而是地下的金矿",
    "entities": []
  },
  {
    "sentence": "那么地下金矿怎么样体现在它的资产负债表，当是一种以采矿权的形式来体现的",
    "entities": []
  },
  {
    "sentence": "哈哈，至于有车、股票都是这样，他们现在是一种权利，一种采矿权，这种海矿权就带有一定的期权的性质",
    "entities": []
  },
  {
    "sentence": "也就是说我虽然在地下，但是我花了很多钱，我买了这些地下挖矿的这些权利，这一点非常重要",
    "entities": []
  },
  {
    "sentence": "比如说我某某，我是某某金矿，我用什么呀",
    "entities": []
  },
  {
    "sentence": "6 毛钱买了一块钱的黄金勘探权，下面是有一块钱的挖出来，比如说值一块钱，但是因为他没挖出来，所以我买他肯定不会用一块钱买，否则被冤大头了，对吧",
    "entities": []
  },
  {
    "sentence": "我肯定是 6 毛钱，我买了一块钱的这样的黄金勘探权",
    "entities": []
  },
  {
    "sentence": "那么好，大家想想看，当国际竞价大涨的时候，一块钱涨到 2 块钱的时候，我这 6 毛钱的这个期权，它的价值是不是也只涨了一倍啊",
    "entities": []
  },
  {
    "sentence": "当然不是，我 6 毛钱的期权相当于怎么样",
    "entities": []
  },
  {
    "sentence": "我能涨到",
    "entities": []
  },
  {
    "sentence": "我涨到了什么呀",
    "entities": []
  },
  {
    "sentence": "我能够挖两块钱的金子",
    "entities": []
  },
  {
    "sentence": "嗯嗯，我原来 6 毛钱挖一块钱的金子涨一倍",
    "entities": []
  },
  {
    "sentence": "我 6 毛钱能挖两块钱的金子，这在干嘛",
    "entities": []
  },
  {
    "sentence": "均价涨了100%，我的权益涨了超过200%，对不对",
    "entities": []
  },
  {
    "sentence": "我的权益涨了超过 200/ 200，也就是说这就是黄金放大期的根本原因，当他怎么样，当他这个金子更值钱的时候，那么我金矿企业手中握有的黄金开产权，它的涨幅是远远的超过了黄金本身涨幅的，这就是它的根本所在啊",
    "entities": []
  },
  {
    "sentence": "黄金上涨的时候会对我的怎么样",
    "entities": []
  },
  {
    "sentence": "会对我的资产负债表有极大的改善",
    "entities": []
  },
  {
    "sentence": "大家可以看一下，因为我不能提名字，但是我们黄金股的一些权重股现在都发了去年的年报，包括今年的业绩月报、快报，大量的股票都是 75% 甚至 100% 的涨",
    "entities": []
  },
  {
    "sentence": "对，在去年我不讲具体的票，大家可能自己去看报表就知道了啊",
    "entities": []
  },
  {
    "sentence": "这么好的涨幅，那你看去年你哪些中国企业能够完成这样的涨幅啊",
    "entities": []
  },
  {
    "sentence": "在一季度甚至在一季度就发生了这么高这么大的一个提升，那么其实都是金矿企业在黄金上涨的时候，它就会交出这么一个让人艳羡的，让人眼睛发红的成绩单哈",
    "entities": []
  },
  {
    "sentence": "所以大家投资黄金股就达到了什么呀",
    "entities": []
  },
  {
    "sentence": "达到了放金，放大黄金的效果，这是第一个原因，其实还有一个原因比较有意思，就是怎么样当你我们重估的时候，这是一个双刃剑，当你重估的时候怎么样金矿更愿意去挖那些金子",
    "entities": []
  },
  {
    "sentence": "把金子挖出来",
    "entities": []
  },
  {
    "sentence": "对，原先比如黄金 400 的时候，我说人民币 400 的时候它可能怎么样",
    "entities": []
  },
  {
    "sentence": "我就挖两个矿，别的矿我先歇业了，现在黄金得 700 了，对吧",
    "entities": []
  },
  {
    "sentence": "这个今天要卖到 700 块钱了",
    "entities": []
  },
  {
    "sentence": "那我可能产能就放满了，每个人都下去挖矿了，对吧",
    "entities": []
  },
  {
    "sentence": "是不是这样啊",
    "entities": []
  },
  {
    "sentence": "也就是说它还有一个产能的扩张，所以我们看到的是两种扩张，第一种就是因为怎样黄金下格上涨带来的利润率的扩张，第二个就是因为黄金上涨，我赶紧去挖黄金带来的产能的扩张，叠加利润率的扩张",
    "entities": []
  },
  {
    "sentence": "黄金的上涨周期大大的利好于黄金开采企业，大家买黄金股不就是买这些黄金的开采企业吗",
    "entities": []
  },
  {
    "sentence": "嗯，不就是买他们的金矿的勘探权，记住，大家买的不是金矿的开采权",
    "entities": []
  },
  {
    "sentence": "那些金矿的开展，现在黄金上涨周期当中，它的不断的重估会对大家带来丰厚的回报，这就是黄金股上涨的时候能扩大黄金涨幅的本质所在，它是有牢固的财务学的基础的",
    "entities": []
  },
  {
    "sentence": "大家有没有听懂",
    "entities": []
  },
  {
    "sentence": "反正我是被张总刚才的这份演讲是吸引住了，然后我也听懂了，虽然我之前可能也确实是这个，你怎么笑场了",
    "entities": []
  },
  {
    "sentence": "没有没有，不笑场，就是",
    "entities": []
  },
  {
    "sentence": "我之前也是，在我本来之前也在想，就是为什么金价涨的时候，我们黄金股的这个上涨的会更多，然后我想到的可能是因为 a 股本身它会有一个流动性，或者它有一个自己的这样的一个波动会更大，所以它会带着我们黄金股上涨",
    "entities": []
  },
  {
    "sentence": "但是刚好张总，其实从这个我们投资到黄金股的这些公司的一个，他们的一个业务的角度出发的，说的是我们就是如果在金价上涨的时候，其实是这个企业的利润率和产其实都是会有一定的扩张，然后就会造成一个杠杆效应，可能涨一斤价，涨一块钱，那我们这个黄金股可能会翻一个 1.5 倍的这样的一个效果",
    "entities": []
  },
  {
    "sentence": "那前面我有一些数据来佐证了，这个大家如果感兴趣的话，我可以那个直播后给大家，我们",
    "entities": []
  },
  {
    "sentence": "的主持人是教一些人才，我这个我是讲基本面的，其实我跟大家做过很多次交流，其实我谈的所有的这样一个指数，其实都是从它基本面出发的啊",
    "entities": []
  },
  {
    "sentence": "那么刚刚说的非常好，因为它本身股票，股票的弹性肯定是大于现货金的这个弹性，那本身它具有一定的因为交易上的流动性会带来一定的溢价，这是有可能的啊",
    "entities": []
  },
  {
    "sentence": "那么是从交易角度出发啊",
    "entities": []
  },
  {
    "sentence": "但是，嗯，我们，我觉得从我的投资角度来看，我一直是以价值它本身的真正的价值为主的，所以我没有考虑这种交易带来的这样一个额外的加成，就是从它本身的业务角度，本身的主营业务的这样一个角度，从它的收入扩张，从它的利润率的提升来看，它就能够完成这样一个所谓的对黄金的这样一个杠杆价乘效应",
    "entities": []
  },
  {
    "sentence": "所以咱们黄金股的这些成分股里面，其实是这个金矿的",
    "entities": []
  },
  {
    "sentence": "金矿在90%，那么大概销售企业是占10%，是",
    "entities": []
  },
  {
    "sentence": "这样，销售就是我们",
    "entities": []
  },
  {
    "sentence": "一些零售的一些，唉，比如说大家知道各种各样的经验吗",
    "entities": []
  },
  {
    "sentence": "怎么老庙老分乡，各种各样",
    "entities": []
  },
  {
    "sentence": "的，那这些其实如果在金价上涨的时候，它也是",
    "entities": []
  },
  {
    "sentence": "一样的，也是非常的好的",
    "entities": []
  },
  {
    "sentence": "为什么道理大家说的这样的话，不是吧",
    "entities": []
  },
  {
    "sentence": "很多人要 challenge 我，唉，这么说它进价也贵了，卖价也贵了，对不对啊",
    "entities": []
  },
  {
    "sentence": "对不对",
    "entities": []
  },
  {
    "sentence": "哈哈哈，那我虽然它可能确实卖了贵了，卖到 720 了",
    "entities": []
  },
  {
    "sentence": "问题是他又没有金矿，他竞价 680 加卖价 720 也赚的辛苦钱",
    "entities": []
  },
  {
    "sentence": "其实不是，真的不是，为什么这个道理，大家去逛逛，今天就知道，我讲是没用的，大家去逛逛，今天就知道即使黄金的这个金店的食物，金的流动性其实很低的，他们付了一屋子的货，其实每天能卖掉几样东西，卖不了几样东西，也就是说它在黄金上涨的时候，所有的黄金零售企业最大的利润来源是什么",
    "entities": []
  },
  {
    "sentence": "是存货的重估啊",
    "entities": []
  },
  {
    "sentence": "你可以把任何一个金典看作一个小小的金矿，上涨的时候它怎么样",
    "entities": []
  },
  {
    "sentence": "它原先的价值成本很低，它本身可能这些东西你看它历史成本这些，比如金镯子做了一个他没卖出去之前，可能原来是 200 块，他就买做好了，对吧",
    "entities": []
  },
  {
    "sentence": "放在那里放到 300 块没人买， 400 块没人买，现在 700 块了，他不是那一次的重工吗",
    "entities": []
  },
  {
    "sentence": "明白了吗",
    "entities": []
  },
  {
    "sentence": "金殿是跟大家完全业态，我其实跟一些机构交流，机构可能没有注意到这个问题，很多看零售的机构，黄金的零售跟所有的零售是不一样的，大家一定要注意，如果大家以后看商业看零售的话，一定要注意以前所有的商业形态，零售最怕的是什么",
    "entities": []
  },
  {
    "sentence": "最怕的就是存货，嗯，因为存货会过期，存货会折旧，存货会怎么样",
    "entities": []
  },
  {
    "sentence": "失去了这个潮流的价值，在这种过程当中你去抵押给银行，对不起，你怎么样啊",
    "entities": []
  },
  {
    "sentence": "十年前的潮品， 100 块钱， 10 年之后你再去抵押，不管你是 LV 还是Gucci，可能你这个老货可能抵押了 50 块钱了，对不对啊",
    "entities": []
  },
  {
    "sentence": "所以它有一个降龄的问题",
    "entities": []
  },
  {
    "sentence": "但是黄金是全世界所有的消费品当中唯一一个没有账龄、没有存货周期的",
    "entities": []
  },
  {
    "sentence": "它的价值对于银行来说就是它的克重",
    "entities": []
  },
  {
    "sentence": "嗯，你在任何一个时点，你都可以按照市价把你的这个克重抵押给银行， 100% 兑现，是不是这样",
    "entities": []
  },
  {
    "sentence": "黄金是一种特别特殊的零售品，大家千万不要把这些金店当做一个零售业态去分析，如果大家都基本面分析的话，请把它当做一个金矿来分析，哈哈",
    "entities": []
  },
  {
    "sentence": "那其实它跟这个",
    "entities": []
  },
  {
    "sentence": "它是一个，当然它没有那个杠杆效应了，但是由于它的存货它的成本会很低，我跟我说了它占名其实很长，很多金店，你比如办十年甚至十年刚开业时候的金镯子可能还放在那里，对吧",
    "entities": []
  },
  {
    "sentence": "是不是这样",
    "entities": []
  },
  {
    "sentence": "当时可能这250，现在 720 了，你说挣了多少资源，对吧",
    "entities": []
  },
  {
    "sentence": "因为它没有一个存货革旧的概念，明白了吗",
    "entities": []
  },
  {
    "sentence": "其实我们做零售，大家如果看零售、看生意，最怕的就是存货周期，你铺满了一满子货，百货店，你看到百货店不是每天卖好多吗",
    "entities": []
  },
  {
    "sentence": "那为什么他不赚钱啊",
    "entities": []
  },
  {
    "sentence": "为什么很多百货店都做了亏了",
    "entities": []
  },
  {
    "sentence": "就是因为它存货过期之后，这些东西只能处理掉了，对吧",
    "entities": []
  },
  {
    "sentence": "但黄金哪会这样",
    "entities": []
  },
  {
    "sentence": "茅台也是",
    "entities": []
  },
  {
    "sentence": "哈哈哈，对吧",
    "entities": []
  },
  {
    "sentence": "我们之前茅台就是上讲时候讲的文字也是这样子",
    "entities": []
  },
  {
    "sentence": "是啊，那这不一样啊",
    "entities": []
  },
  {
    "sentence": "好的好的，OK，唉，我看到评论里有人说这个还有茅台酒，跟我想到一起去啊",
    "entities": []
  },
  {
    "sentence": "那你们讲的这个酒也是，但是茅酒也不，茅台确实它是一个耐处的场景，但是茅台跟黄金还是不一样的，黄金可以无损的折旧，它具有无限的流动性",
    "entities": []
  },
  {
    "sentence": "茅台它只有一个，在很好的情况下它只有一个估值的价值",
    "entities": []
  },
  {
    "sentence": "有的银行可能会认，可能其实它的量是非常有限的",
    "entities": []
  },
  {
    "sentence": "大家去看看二手茅台市场，老茅台市场就知道了，其实，嗯，很多只是有价无市啊",
    "entities": []
  },
  {
    "sentence": "其实中国茅台其实囤的已经不少了，每年的茅台喝掉的可能还没囤的多，对吧",
    "entities": []
  },
  {
    "sentence": "其实这个市场的流动性就是它的容量，我不说大家的容量其实远远不如黄金的，其实大家把黄金是可以分分钟的变现的，但是你要把一个老茅台按照你想要的价格变现，其实非常等一等，非常难",
    "entities": []
  },
  {
    "sentence": "的，所以说饮酒买茅台不如买黄金",
    "entities": []
  },
  {
    "sentence": "那不同的思路，你囤酒的那个什么欧洲有好多贵族酒庄，都是捧了好多年的酒，对吧",
    "entities": []
  },
  {
    "sentence": "你也不能说这种生活不是一个很好的生活方式，对吧",
    "entities": []
  },
  {
    "sentence": "生活加投资方式这个不一样，但是黄金其实就冲着投资来的，那个囤酒你可能还是跟你个人品味，对吧",
    "entities": []
  },
  {
    "sentence": "这种欣赏那种有关的",
    "entities": []
  },
  {
    "sentence": "但是咱黄金其实也能欣赏，对吧",
    "entities": []
  },
  {
    "sentence": "可以做成金饰之后也可以带来身上",
    "entities": []
  },
  {
    "sentence": "那所以归档了，你就跟投资可能",
    "entities": []
  },
  {
    "sentence": "就是另一个",
    "entities": []
  },
  {
    "sentence": "工匠",
    "entities": []
  },
  {
    "sentence": "有消费的一个因素",
    "entities": []
  },
  {
    "sentence": "对，好的，那我们最后就聊一个",
    "entities": []
  },
  {
    "sentence": "嗯，可能很多朋友都非常非常关心的，就是说既然你说现在，噢这个黄金涨的不错，黄金股也是它的一个放大气",
    "entities": []
  },
  {
    "sentence": "那我现在感觉涨最近短期涨的是有点高啊，那现在能不能是一个合适的一个入场时机",
    "entities": []
  },
  {
    "sentence": "可能前面咱已经讲了，对，之后再把这个问题再给他回答，哈哈哈",
    "entities": []
  },
  {
    "sentence": "我们这个讲过很多次了，这个我觉得没有什么问题，因为确实黄金的投资它本身就是一个右侧的投资，那么现在来看就是它长，因为我也不具体",
    "entities": []
  },
  {
    "sentence": "再说了，它长期的这个逻辑，中期的逻辑其实都前面讲的逻辑都没有变化，那么在这种情况下，其实黄金其实还是应该怎么说",
    "entities": []
  },
  {
    "sentence": "肯定是非常值得关注和参与的，当然跟大家手上的投有关，大家如果现在已经满仓黄金了，那我也不建议继续追加，对吧",
    "entities": []
  },
  {
    "sentence": "对，但是如果大家现在还没有黄金的这样一个持仓的话，那么黄金股其实是非常还值，还是永远值得大家配置的，这我说的是永远指的是黄金类的资产，其实应该是每个人一生当中的任何时点都应该有一定比例的这样一个资产啊",
    "entities": []
  },
  {
    "sentence": "嗯，这个是我对投资的这样一个总结，因为世界上到今天为止还没有任何一种资产拥有黄金的这个两个功能，一个是极端抗通胀，一个是极端避风险，这两个功能没有一个市场能够替代",
    "entities": []
  },
  {
    "sentence": "那么好，大家在这样一个漫长的人生旅途当中，我相信抗东上皮风险也是每个人、每个家庭需要做的事情，对不对啊",
    "entities": []
  },
  {
    "sentence": "那么既然是这样，那达里奥的那句话一点都没错，就是在投资组合当中拥有一定的黄金类资产，不管多少，那么是跟大家的风险偏好有关，但是",
    "entities": []
  },
  {
    "sentence": "一定要有，不然你不是不懂经济学就是不懂历史学",
    "entities": []
  },
  {
    "sentence": "对，这句我记住了",
    "entities": []
  },
  {
    "sentence": "对对对，看到有很多评论对我们这个张总的这个今天的交流非常觉得收获满满啊",
    "entities": []
  },
  {
    "sentence": "那也",
    "entities": []
  },
  {
    "sentence": "太客气了，反正经常跟大家聊聊，因为黄金是大家有什么问题",
    "entities": []
  },
  {
    "sentence": "嗯，跟",
    "entities": []
  },
  {
    "sentence": "大家可能有些问题，我们在前面已经回答过了，大家可以看一下，有，有",
    "entities": []
  },
  {
    "sentence": "什么信，有什么信的问题我再来打败",
    "entities": []
  },
  {
    "sentence": "没问题，感觉",
    "entities": []
  },
  {
    "sentence": "差不多了，提的问题前面其实都有回答过，大家可以看一下回放，我们这场就干货满满的",
    "entities": []
  },
  {
    "sentence": "谈不上，我觉得跟大家非常有意思，就是还有点时间，是",
    "entities": []
  },
  {
    "sentence": "吧",
    "entities": []
  },
  {
    "sentence": "对，咱们也没事，我们也可以提前结束",
    "entities": []
  },
  {
    "sentence": "不用提前结束，那倒挺",
    "entities": []
  },
  {
    "sentence": "好的",
    "entities": []
  },
  {
    "sentence": "交流啊",
    "entities": []
  },
  {
    "sentence": "对，黄金最近的一个也",
    "entities": []
  },
  {
    "sentence": "不是最近一段心得就是刚说到就是黄金上涨的时候对黄金矿特别有利",
    "entities": []
  },
  {
    "sentence": "为什么道理呢",
    "entities": []
  },
  {
    "sentence": "其实黄金矿和煤矿什么呢",
    "entities": []
  },
  {
    "sentence": "也不是特别一样，大家其实一定要注意一下，黄金矿有它一些特质，因为其实我是到黄金矿里去看过的",
    "entities": []
  },
  {
    "sentence": "嗯，黄金矿，大家所谓的黄金矿知道是啥玩意吗",
    "entities": []
  },
  {
    "sentence": "它并不是一头黄金，什么狗头金，这很少的",
    "entities": []
  },
  {
    "sentence": "它这个东西非常有意思，它是古代，就是可能含黄金的液体，有可能是火山的，有可能是河流的，干掉之后，然后压在了黄金",
    "entities": []
  },
  {
    "sentence": "所以金矿它里边跟那个煤矿不一样，煤矿是一团团、一层层的，金矿是一条线，它是一条线，就是古代比如说你泉河，河里有很多，当然就有可能是龙岩河，河里有很多黄金，对吧",
    "entities": []
  },
  {
    "sentence": "然后它干掉之后变成了一条矿脉",
    "entities": []
  },
  {
    "sentence": "这个矿脉就有意思了，因为你煤矿的话，那么我们现在中国的这个开采权就是这块地，懂一块，唉，煤矿这块地是你的，哈哈哈，你不要偷偷挖出去，但金矿不一样，金矿它是什么呀",
    "entities": []
  },
  {
    "sentence": "它是一条河，所以我们经常会看到那些龙头企业，很多企业经常会恢复啊",
    "entities": []
  },
  {
    "sentence": "我又发明了多少储量",
    "entities": []
  },
  {
    "sentence": "又发现了什么",
    "entities": []
  },
  {
    "sentence": "其实这个有意思，因为你顺着这条河挖过去，它往往在这块限定的这个方块的地方其实没有到头，但是因为河怎么会在这里到头呢",
    "entities": []
  },
  {
    "sentence": "往往它还能延过去，所以大家要对中国有信心，大家对中国有信心，我对中国是最有信心的，因为我一直跟大家说中国人干什么都行，干黄金特别信",
    "entities": []
  },
  {
    "sentence": "嗯，中国自古到今没有什么大的金矿，自古到今没有特别有名的富矿",
    "entities": []
  },
  {
    "sentence": "大家不相信你给我讲一个出来，没有中国银矿，还有云南以前有猪蹄银，中国银矿也，还有铜矿也有，但是金矿大的真没有",
    "entities": []
  },
  {
    "sentence": "但是怎么样",
    "entities": []
  },
  {
    "sentence": "中国历史上一直有黄金，而且到了今天，中国更不得了",
    "entities": []
  },
  {
    "sentence": "中国是世界黄金产量的第一名， 300 多吨黄金，全世界一年产量 3, 500 吨，我们中国占 11%- 12%",
    "entities": []
  },
  {
    "sentence": "哈哈，非常厉害，我们中国黄金非常平，但是黄金还能采这么多，什么道理呢",
    "entities": []
  },
  {
    "sentence": "就是因为人家那个金矿可能会去采什么品位非常高的，怎么在国际上百分之 6 克每吨算是好的啊",
    "entities": []
  },
  {
    "sentence": "肯定采了 3 克每吨在国际上也能裁，但是我只有我们中国 1 克每吨不到，我就裁了",
    "entities": []
  },
  {
    "sentence": "好卷",
    "entities": []
  },
  {
    "sentence": "很卷，所以我们的坑口价是比较高",
    "entities": []
  },
  {
    "sentence": "这个到以后有时间再跟大家介绍一下每家金矿的那个成本是多少啊",
    "entities": []
  },
  {
    "sentence": "嗯，今天因为我一方面我不太适合讲每家，嗯，讲成风股啊",
    "entities": []
  },
  {
    "sentence": "另一方这个今天可能时间所限，我们跟国际上比较一下巴里克黄金的成本价，它挖出来是多少啊",
    "entities": []
  },
  {
    "sentence": "非洲人挖出来是多少",
    "entities": []
  },
  {
    "sentence": "我们中国人挖出来是多少",
    "entities": []
  },
  {
    "sentence": "那为什么我们中国还挖那么多啊",
    "entities": []
  },
  {
    "sentence": "非常有意思",
    "entities": []
  },
  {
    "sentence": "那么我今天这个主要讲的就是大家一定要相信中国的这样一个黄金的这样一个生产能力，就是因为我们中国怎么样发展了一整套的，比如说络合物氢化法、氢化骆合物法，将这么很平静的黄金矿都能炼出黄金来啊",
    "entities": []
  },
  {
    "sentence": "所以中国对挖矿的潜力是非常大的，中国的采矿权更值钱",
    "entities": []
  },
  {
    "sentence": "人家说嘛，你挖出去这个地方，比如说我巴克里，巴里克黄金，原来我批了一块 6 克的，嗯，对吧",
    "entities": []
  },
  {
    "sentence": "挖出去 3 克的还是我的",
    "entities": []
  },
  {
    "sentence": "再挖出去一克的我就不要了",
    "entities": []
  },
  {
    "sentence": "那这个境况有限嘛，对吧",
    "entities": []
  },
  {
    "sentence": "嗯，但是我们中国不一样，我们中国挖出去只要还有一点，我都是储备产能，那这个明白了吗",
    "entities": []
  },
  {
    "sentence": "有多少我们挖",
    "entities": []
  },
  {
    "sentence": "有多少可以挖多少",
    "entities": []
  },
  {
    "sentence": "所以我们大家看一下现在的这样一个新闻，大家都知道我们中国现在一直在黄金上涨的时候，中国一直在宣布发现了很多大型金矿，这个大家可以注意一下最近的新闻，这个其实非常有在就在中国会发生这个事儿，一方面中国对黄金确实是非常有感情的，中国历史上有唯有一只全世界唯一一只专门寻找黄金的部队，武警黄金总队，哈哈，这是中国",
    "entities": []
  },
  {
    "sentence": "全",
    "entities": []
  },
  {
    "sentence": "世界唯一一个寻找黄金的部队",
    "entities": []
  },
  {
    "sentence": "都在我们中国，大家服气不服气",
    "entities": []
  },
  {
    "sentence": "哈哈，武警黄金总的全世界唯一一支寻找专门寻找黄金的部队，为国寻金，为国土金，而且我们中国能够开采非常贫瘠的金矿，而且可以把成本价压到非常低的这样的位置啊",
    "entities": []
  },
  {
    "sentence": "他们巴克里，巴里克黄金那个挖这么富的矿 180 元每克的成本，我们挖这么平低的矿也能做到 300 元每克的成本",
    "entities": []
  },
  {
    "sentence": "他们可能是六克每吨，我们只有一克不到每吨也能做到，所以在很多外国人看来不是金矿的情况，我们也能把它变成金矿，哈哈哈，所以大家一定要对中国有信心，中国的黄金股也有信心，因为在黄金上涨的周期当中，我们不管看到什么样产能的上升，对，不",
    "entities": []
  },
  {
    "sentence": "难看到什么，那个我们利润率的上市还能看到怎么样",
    "entities": []
  },
  {
    "sentence": "还能看到他们储量的上升，他们还能挖出新的情况，这也是中国一个非常特色的地方，可能今天时间不多，也不能跟大家细讲，所以黄金在中国其实是个非常有意思的这个行业，我们中国人在黄金上、历史上倾注了大人的心血，也是世界上最懂得奠金的国家，不能说世界上黄金最富、储量最大的国家，中国不是世界上那个黄金资源最丰富的国家，中国也不是，但是中国是最懂黄金的国家，中国是最擅长于奠金的国家，这个绝对是",
    "entities": []
  },
  {
    "sentence": "哈哈哈，所以中国的黄金股整个板块拥有，其他国家是没有的",
    "entities": []
  },
  {
    "sentence": "这样一个特质，非常卷，哈哈哈，在这种卷的过程当中，他说买票肯定是要买卷的票了，对吧",
    "entities": []
  },
  {
    "sentence": "肯定是要买这一些乐观向上、具有扩张的动力的票，对不对啊",
    "entities": []
  },
  {
    "sentence": "那你肯定是这样吗",
    "entities": []
  },
  {
    "sentence": "躺平的票他去买它干嘛，对吧啊",
    "entities": []
  },
  {
    "sentence": "那么其实中国的黄金股一定是符合你们这种要求的，嗯，符合",
    "entities": []
  },
  {
    "sentence": "这种要求",
    "entities": []
  },
  {
    "sentence": "所以说如果看我们黄金股就可以关注一下我们这只资金，我们这只资金场内的话是517520，场外的话 c 类份额是020412",
    "entities": []
  },
  {
    "sentence": "大家可以在公屏",
    "entities": []
  },
  {
    "sentence": "上这个名字起的还特别好",
    "entities": []
  },
  {
    "sentence": "对，这个 520 其实也是我们",
    "entities": []
  },
  {
    "sentence": "当时觉得特别适合黄金，对吧",
    "entities": []
  },
  {
    "sentence": "因为现在也说一下，平常那经过黄金涨，确实钻石跌了，黄金涨了给对很多人的消费习惯也造成了这个影响啊",
    "entities": []
  },
  {
    "sentence": "原先 520 大家想到的是钻石，对，但是我们以前，包括我们那个时代，上海人结婚是要送钻戒的",
    "entities": []
  },
  {
    "sentence": "现在金戒指也可以",
    "entities": []
  },
  {
    "sentence": "现在不但不一定是钻戒，而且杨丈母娘强制要求要 3 斤了，哈哈哈，你跟上海人结婚好像不要三斤的，现在也要三斤了，哈哈，所以这个确实呢",
    "entities": []
  },
  {
    "sentence": "嗯，黄金对我们中国的这样一个历史文化是影响甚远，而且是就在今天还在不断的发生新的变化",
    "entities": []
  },
  {
    "sentence": "是的，大家如果有关注到黄金，然后可以再关注一下我们黄金股，如果关注黄金股的话，场外的话可以关注一下我们的这个永宁中证沪港、沪深港黄金产业股票场外链接，那我们的份额的代码是020412",
    "entities": []
  },
  {
    "sentence": "哈，那这场直播呢",
    "entities": []
  },
  {
    "sentence": "我们今天也是到这了，感谢张总为我们讲这么多的干货，也感谢各位小伙伴讲讲故事吧",
    "entities": []
  },
  {
    "sentence": "对，感谢小伙伴们，今天非常频繁的跟我们进行一个互动，然后向我们提问，也向我们夸赞了一下张总",
    "entities": []
  },
  {
    "sentence": "那我们下次我们还会把张总再请到我们主播给大家",
    "entities": []
  },
  {
    "sentence": "讲故事，黄金的故事讲不完太多",
    "entities": []
  },
  {
    "sentence": "对黄金的故事我们下次其实这次还留了很多影子，我们下次还可以用这些钩子，我们继续来讲这些故事",
    "entities": []
  },
  {
    "sentence": "好的，那我们今天的直播就到这儿了，那相信大家应该有所收获",
    "entities": []
  },
  {
    "sentence": "好的，我们拜拜吧",
    "entities": []
  },
  {
    "sentence": "嗯，再见，下一位",
    "entities": []
  },
  {
    "sentence": "准备对手的挑衅，自然的现实来说是最难救的",
    "entities": []
  },
  {
    "sentence": "现实的强大都不足以让你动摇一分一毫",
    "entities": []
  },
  {
    "sentence": "你说我吗",
    "entities": []
  },
  {
    "sentence": "对，说的就是你",
    "entities": []
  },
  {
    "sentence": "你努力的样子真的很帅",
    "entities": []
  },
  {
    "sentence": "只要你够坚定，每一条都是对的路",
    "entities": []
  },
  {
    "sentence": "财经大学国际金融，除非你不想赢，否则没人能让你输",
    "entities": []
  },
  {
    "sentence": "赢过平凡，赢得梦想，赢过恐惧，赢得掌声，赢过阻碍，赢得尊重，赢到满足，赢到不满足",
    "entities": []
  },
  {
    "sentence": "总有人在为失败找借口，但你知道那些打不倒你的都会让你变得更强",
    "entities": []
  },
  {
    "sentence": "去赢吧，就算跌倒也没关系，就算渺小也没关系，就算孤独也没",
    "entities": []
  }
]